handlerchief/__init__.py
handlerchief/chain_handler.py
handlerchief/error_wrapper.py
handlerchief/i_handler.py
handlerchief/i_middleware_handler.py
handlerchief/multi_handler.py
handlerchief/pipe_handler.py
Handlerchief-0.1.0.dist-info/LICENSE
Handlerchief-0.1.0.dist-info/METADATA
Handlerchief-0.1.0.dist-info/WHEEL
Handlerchief-0.1.0.dist-info/top_level.txt
Handlerchief-0.1.0.dist-info/RECORD
