Metadata-Version: 2.1
Name: Handlerchief
Version: 0.1.0
Summary: Handlers.
Home-page: https://github.com/kokaib/python-handlerchief
Author: Bálint Kókai
Author-email: galsaizoltan1@gmail.com
License: UNKNOWN
Platform: UNKNOWN
Classifier: Programming Language :: Python :: 3
Classifier: License :: OSI Approved :: MIT License
Classifier: Operating System :: OS Independent
Requires-Python: >=3.7
License-File: LICENSE
Requires-Dist: pathlib (>=1.0.1)
